[
  {
    "partner": "NJ",
    "year": "2001-01-23T04:56:07.000+00:00",
    "hs2": "886",
    "reporter": "SJ",
    "value": 75
  },
  {
    "partner": "NJ",
    "year": "2002-01-23T04:56:07.000+00:00",
    "hs2": "88",
    "reporter": "SJ",
    "value": 34
  },
  {
    "partner": "NJ",
    "year": "2003-01-23T04:56:07.000+00:00",
    "hs2": "88",
    "reporter": "SJ",
    "value": 78
  },
  {
    "partner": "NJ",
    "year": "2004-01-23T04:56:07.000+00:00",
    "hs2": "88",
    "reporter": "SJ",
    "value": 10
  },
  {
    "partner": "NJ",
    "year": "2088-01-23T04:56:07.000+00:00",
    "hs2": "88",
    "reporter": "SJ",
    "value": 64
  }
]
